vanity/__init__.py
vanity/_frontend.py
vanity/_version.py
vanity/example.py
vanity/vanity.py
vanity/labextension/vanity-0.1.0.tgz
vanity/nbextension/__init__.py
vanity/nbextension/static/extension.js
vanity/nbextension/static/index.js
vanity/nbextension/static/index.js.LICENSE.txt
vanity/nbextension/static/index.js.map
vanity/nbextension/static/vendors-node_modules_stencil_core_internal_client_shadow-css_js.index.js
vanity/nbextension/static/vendors-node_modules_stencil_core_internal_client_shadow-css_js.index.js.map
vanity-widget/__init__.py
vanity-widget/_frontend.py
vanity-widget/_version.py
vanity-widget/example.py
vanity-widget/vanity.py
vanity-widget/labextension/vanity-0.1.0.tgz
vanity-widget/nbextension/__init__.py
vanity-widget/nbextension/static/extension.js
vanity-widget/nbextension/static/index.js
vanity-widget/nbextension/static/index.js.LICENSE.txt
vanity-widget/nbextension/static/index.js.map
vanity-widget/nbextension/static/vendors-node_modules_stencil_core_internal_client_shadow-css_js.index.js
vanity-widget/nbextension/static/vendors-node_modules_stencil_core_internal_client_shadow-css_js.index.js.map
vanity_widget-0.1.0.data/data/etc/jupyter/nbconfig/notebook.d/vanity.json
vanity_widget-0.1.0.data/data/share/jupyter/lab/extensions/vanity-0.1.0.tgz
vanity_widget-0.1.0.data/data/share/jupyter/nbextensions/vanity/extension.js
vanity_widget-0.1.0.data/data/share/jupyter/nbextensions/vanity/index.js
vanity_widget-0.1.0.data/data/share/jupyter/nbextensions/vanity/index.js.LICENSE.txt
vanity_widget-0.1.0.data/data/share/jupyter/nbextensions/vanity/index.js.map
vanity_widget-0.1.0.data/data/share/jupyter/nbextensions/vanity/vendors-node_modules_stencil_core_internal_client_shadow-css_js.index.js
vanity_widget-0.1.0.data/data/share/jupyter/nbextensions/vanity/vendors-node_modules_stencil_core_internal_client_shadow-css_js.index.js.map
vanity_widget-0.1.0.dist-info/LICENSE.txt
vanity_widget-0.1.0.dist-info/METADATA
vanity_widget-0.1.0.dist-info/WHEEL
vanity_widget-0.1.0.dist-info/top_level.txt
vanity_widget-0.1.0.dist-info/RECORD
