Metadata-Version: 2.1
Name: vanity-widget
Version: 0.1.0
Summary: A Custom Jupyter Widget Library
Home-page: https://github.com/vanity/vanity
Author: ilan
Author-email: im334@cornell.edu
License: BSD
Keywords: Jupyter,Widgets,IPython
Platform: Linux
Platform: Mac OS X
Platform: Windows
Classifier: Intended Audience :: Developers
Classifier: Intended Audience :: Science/Research
Classifier: License :: OSI Approved :: BSD License
Classifier: Programming Language :: Python
Classifier: Programming Language :: Python :: 3
Classifier: Programming Language :: Python :: 3.4
Classifier: Programming Language :: Python :: 3.5
Classifier: Programming Language :: Python :: 3.6
Classifier: Programming Language :: Python :: 3.7
Classifier: Framework :: Jupyter
License-File: LICENSE.txt
Requires-Dist: ipywidgets (>=7.0.0)
